{
  "kind": "ResourceEditor",
  "apiVersion": "ui.k8s.appscode.com/v1alpha1",
  "metadata": {
    "name": "sql.azure.kubedb.com-v1alpha1-mssqlmanagedinstances",
    "creationTimestamp": null,
    "labels": {
      "k8s.io/group": "sql.azure.kubedb.com",
      "k8s.io/kind": "MSSQLManagedInstance",
      "k8s.io/resource": "mssqlmanagedinstances",
      "k8s.io/version": "v1alpha1"
    }
  },
  "spec": {
    "resource": {
      "group": "sql.azure.kubedb.com",
      "version": "v1alpha1",
      "name": "mssqlmanagedinstances",
      "kind": "MSSQLManagedInstance",
      "scope": "Cluster"
    },
    "ui": {
      "editor": {
        "name": "sqlazurekubedbcom-mssqlmanagedinstance-editor",
        "version": "v0.10.0",
        "sourceRef": {
          "apiGroup": "source.toolkit.fluxcd.io",
          "kind": "HelmRepository",
          "name": "appscode-charts-oci"
        }
      },
      "enforceQuota": false
    }
  }
}