{
  "kind": "ResourceEditor",
  "apiVersion": "ui.k8s.appscode.com/v1alpha1",
  "metadata": {
    "name": "kubedb.com-v1alpha2-mongodbs",
    "creationTimestamp": null,
    "labels": {
      "k8s.io/group": "kubedb.com",
      "k8s.io/kind": "MongoDB",
      "k8s.io/resource": "mongodbs",
      "k8s.io/version": "v1alpha2"
    }
  },
  "spec": {
    "resource": {
      "group": "kubedb.com",
      "version": "v1alpha2",
      "name": "mongodbs",
      "kind": "MongoDB",
      "scope": "Namespaced"
    },
    "ui": {
      "options": {
        "name": "kubedbcom-mongodb-editor-options",
        "version": "sha256:31ed9988fb428e0b953758b9d0e28d04e8210d8e0d8130668ef3f0c7119764e7",
        "sourceRef": {
          "apiGroup": "source.toolkit.fluxcd.io",
          "kind": "HelmRepository",
          "name": "appscode-charts-oci"
        }
      },
      "editor": {
        "name": "kubedbcom-mongodb-editor",
        "version": "sha256:00bae4f709003cb2df681acfb40619ec15bfcdf6afe7acef67e5f8db395c3faf",
        "sourceRef": {
          "apiGroup": "source.toolkit.fluxcd.io",
          "kind": "HelmRepository",
          "name": "appscode-charts-oci"
        }
      },
      "enforceQuota": true,
      "actions": [
        {
          "name": "Backups",
          "items": [
            {
              "name": "Configure Backup",
              "icons": [
                {
                  "src": "https://cdn.appscode.com/k8s/icons/action-icons/configure-backup.svg",
                  "type": "image/svg+xml"
                }
              ],
              "operationId": "edit-self-backupconfiguration",
              "flow": "standalone-edit",
              "editor": {
                "name": "kubedbcom-mongodb-editor",
                "version": "sha256:00bae4f709003cb2df681acfb40619ec15bfcdf6afe7acef67e5f8db395c3faf",
                "sourceRef": {
                  "apiGroup": "source.toolkit.fluxcd.io",
                  "kind": "HelmRepository",
                  "name": "appscode-charts-oci"
                }
              },
              "enforceQuota": false
            },
            {
              "name": "Restore",
              "icons": [
                {
                  "src": "https://cdn.appscode.com/k8s/icons/action-icons/restore.svg",
                  "type": "image/svg+xml"
                }
              ],
              "operationId": "create-restoresession",
              "flow": "standalone-create",
              "editor": {
                "name": "corekubestashcom-restoresession-editor-options",
                "version": "sha256:66fb1eb161d84a80029bac82e3dcae40b657a434a5656fb329fc84748a72e19a",
                "sourceRef": {
                  "apiGroup": "source.toolkit.fluxcd.io",
                  "kind": "HelmRepository",
                  "name": "appscode-charts-oci"
                }
              },
              "enforceQuota": false
            }
          ]
        },
        {
          "name": "Operations",
          "items": [
            {
              "name": "Update Version",
              "icons": [
                {
                  "src": "https://cdn.appscode.com/k8s/icons/action-icons/version.svg",
                  "type": "image/svg+xml"
                }
              ],
              "operationId": "create-opsrequest-upgrade",
              "flow": "standalone-create",
              "editor": {
                "name": "opskubedbcom-mongodbopsrequest-editor",
                "version": "sha256:26ab7f015b4f08436a832194f4272a4038291c0a362c998840db40f01c1c31b0",
                "sourceRef": {
                  "apiGroup": "source.toolkit.fluxcd.io",
                  "kind": "HelmRepository",
                  "name": "appscode-charts-oci"
                }
              },
              "enforceQuota": false
            },
            {
              "name": "Restart",
              "icons": [
                {
                  "src": "https://cdn.appscode.com/k8s/icons/action-icons/restart.svg",
                  "type": "image/svg+xml"
                }
              ],
              "operationId": "create-opsrequest-restart",
              "flow": "standalone-create",
              "editor": {
                "name": "opskubedbcom-mongodbopsrequest-editor",
                "version": "sha256:26ab7f015b4f08436a832194f4272a4038291c0a362c998840db40f01c1c31b0",
                "sourceRef": {
                  "apiGroup": "source.toolkit.fluxcd.io",
                  "kind": "HelmRepository",
                  "name": "appscode-charts-oci"
                }
              },
              "enforceQuota": false
            },
            {
              "name": "Reconfigure",
              "icons": [
                {
                  "src": "https://cdn.appscode.com/k8s/icons/action-icons/reconfigure.svg",
                  "type": "image/svg+xml"
                }
              ],
              "operationId": "create-opsrequest-reconfigure",
              "flow": "standalone-create",
              "editor": {
                "name": "opskubedbcom-mongodbopsrequest-editor",
                "version": "sha256:26ab7f015b4f08436a832194f4272a4038291c0a362c998840db40f01c1c31b0",
                "sourceRef": {
                  "apiGroup": "source.toolkit.fluxcd.io",
                  "kind": "HelmRepository",
                  "name": "appscode-charts-oci"
                }
              },
              "enforceQuota": false
            }
          ]
        },
        {
          "name": "Scaling",
          "items": [
            {
              "name": "Horizontal Scale",
              "icons": [
                {
                  "src": "https://cdn.appscode.com/k8s/icons/action-icons/horizontal_scale.svg",
                  "type": "image/svg+xml"
                }
              ],
              "operationId": "create-opsrequest-horizontalscaling",
              "flow": "standalone-create",
              "disabledTemplate": "{{ not (or (hasKey .spec \"shardTopology\") ( hasKey .spec \"replicaSet\"))}}\n",
              "editor": {
                "name": "opskubedbcom-mongodbopsrequest-editor",
                "version": "sha256:26ab7f015b4f08436a832194f4272a4038291c0a362c998840db40f01c1c31b0",
                "sourceRef": {
                  "apiGroup": "source.toolkit.fluxcd.io",
                  "kind": "HelmRepository",
                  "name": "appscode-charts-oci"
                }
              },
              "enforceQuota": true
            },
            {
              "name": "Vertical Scale",
              "icons": [
                {
                  "src": "https://cdn.appscode.com/k8s/icons/action-icons/vertical_scale.svg",
                  "type": "image/svg+xml"
                }
              ],
              "operationId": "create-opsrequest-verticalscaling",
              "flow": "standalone-create",
              "editor": {
                "name": "opskubedbcom-mongodbopsrequest-editor",
                "version": "sha256:26ab7f015b4f08436a832194f4272a4038291c0a362c998840db40f01c1c31b0",
                "sourceRef": {
                  "apiGroup": "source.toolkit.fluxcd.io",
                  "kind": "HelmRepository",
                  "name": "appscode-charts-oci"
                }
              },
              "enforceQuota": true
            },
            {
              "name": "Expand Volume",
              "icons": [
                {
                  "src": "https://cdn.appscode.com/k8s/icons/action-icons/expand.svg",
                  "type": "image/svg+xml"
                }
              ],
              "operationId": "create-opsrequest-volumeexpansion",
              "flow": "standalone-create",
              "editor": {
                "name": "opskubedbcom-mongodbopsrequest-editor",
                "version": "sha256:26ab7f015b4f08436a832194f4272a4038291c0a362c998840db40f01c1c31b0",
                "sourceRef": {
                  "apiGroup": "source.toolkit.fluxcd.io",
                  "kind": "HelmRepository",
                  "name": "appscode-charts-oci"
                }
              },
              "enforceQuota": true
            }
          ]
        },
        {
          "name": "Autoscaling",
          "items": [
            {
              "name": "Compute",
              "icons": [
                {
                  "src": "https://cdn.appscode.com/k8s/icons/action-icons/compute.svg",
                  "type": "image/svg+xml"
                }
              ],
              "operationId": "create-opsrequest-compute",
              "flow": "standalone-create",
              "editor": {
                "name": "autoscalingkubedbcom-mongodbautoscaler-editor",
                "version": "sha256:87137457c81c1a02fb536eb9f5015390211a12091fe80157c8d0a57d20f913ef",
                "sourceRef": {
                  "apiGroup": "source.toolkit.fluxcd.io",
                  "kind": "HelmRepository",
                  "name": "appscode-charts-oci"
                }
              },
              "enforceQuota": true
            },
            {
              "name": "Storage",
              "icons": [
                {
                  "src": "https://cdn.appscode.com/k8s/icons/action-icons/storage.svg",
                  "type": "image/svg+xml"
                }
              ],
              "operationId": "create-opsrequest-storage",
              "flow": "standalone-create",
              "editor": {
                "name": "autoscalingkubedbcom-mongodbautoscaler-editor",
                "version": "sha256:87137457c81c1a02fb536eb9f5015390211a12091fe80157c8d0a57d20f913ef",
                "sourceRef": {
                  "apiGroup": "source.toolkit.fluxcd.io",
                  "kind": "HelmRepository",
                  "name": "appscode-charts-oci"
                }
              },
              "enforceQuota": true
            }
          ]
        },
        {
          "name": "Security \u0026 Monitoring",
          "items": [
            {
              "name": "TLS Configure",
              "icons": [
                {
                  "src": "https://cdn.appscode.com/k8s/icons/action-icons/configure.svg",
                  "type": "image/svg+xml"
                }
              ],
              "operationId": "create-opsrequest-reconfiguretls",
              "flow": "standalone-create",
              "editor": {
                "name": "opskubedbcom-mongodbopsrequest-editor",
                "version": "sha256:26ab7f015b4f08436a832194f4272a4038291c0a362c998840db40f01c1c31b0",
                "sourceRef": {
                  "apiGroup": "source.toolkit.fluxcd.io",
                  "kind": "HelmRepository",
                  "name": "appscode-charts-oci"
                }
              },
              "enforceQuota": false
            },
            {
              "name": "Monitoring",
              "icons": [
                {
                  "src": "https://cdn.appscode.com/k8s/icons/action-icons/monitor.svg",
                  "type": "image/svg+xml"
                }
              ],
              "operationId": "edit-self-monitoring",
              "flow": "standalone-edit",
              "editor": {
                "name": "kubedbcom-mongodb-editor",
                "version": "sha256:00bae4f709003cb2df681acfb40619ec15bfcdf6afe7acef67e5f8db395c3faf",
                "sourceRef": {
                  "apiGroup": "source.toolkit.fluxcd.io",
                  "kind": "HelmRepository",
                  "name": "appscode-charts-oci"
                }
              },
              "enforceQuota": false
            }
          ]
        }
      ]
    },
    "icons": [
      {
        "src": "https://cdn.appscode.com/k8s/icons/kubedb.com/mongodbs.svg",
        "type": "image/svg+xml"
      },
      {
        "src": "https://cdn.appscode.com/k8s/icons/kubedb.com/mongodbs.png",
        "type": "image/png"
      }
    ],
    "variants": [
      {
        "name": "default",
        "selector": {
          "matchExpressions": [
            {
              "key": "charts.x-helm.dev/is-default-preset",
              "operator": "In",
              "values": [
                "true",
                "kubedb"
              ]
            }
          ]
        }
      }
    ]
  }
}