{
  "kind": "ResourceEditor",
  "apiVersion": "ui.k8s.appscode.com/v1alpha1",
  "metadata": {
    "name": "meta.k8s.appscode.com-v1alpha1-menuoutlines",
    "creationTimestamp": null,
    "labels": {
      "k8s.io/group": "meta.k8s.appscode.com",
      "k8s.io/kind": "MenuOutline",
      "k8s.io/resource": "menuoutlines",
      "k8s.io/version": "v1alpha1"
    }
  },
  "spec": {
    "resource": {
      "group": "meta.k8s.appscode.com",
      "version": "v1alpha1",
      "name": "menuoutlines",
      "kind": "MenuOutline",
      "scope": "Cluster"
    },
    "ui": {
      "editor": {
        "name": "metak8sappscodecom-menuoutline-editor",
        "version": "v0.4.21",
        "sourceRef": {
          "apiGroup": "source.toolkit.fluxcd.io",
          "kind": "HelmRepository",
          "name": "appscode-charts-oci"
        }
      },
      "enforceQuota": false
    }
  }
}