{
  "kind": "ResourceEditor",
  "apiVersion": "ui.k8s.appscode.com/v1alpha1",
  "metadata": {
    "name": "work.open-cluster-management.io-v1alpha1-manifestworkreplicasets",
    "creationTimestamp": null,
    "labels": {
      "k8s.io/group": "work.open-cluster-management.io",
      "k8s.io/kind": "ManifestWorkReplicaSet",
      "k8s.io/resource": "manifestworkreplicasets",
      "k8s.io/version": "v1alpha1"
    }
  },
  "spec": {
    "resource": {
      "group": "work.open-cluster-management.io",
      "version": "v1alpha1",
      "name": "manifestworkreplicasets",
      "kind": "ManifestWorkReplicaSet",
      "scope": "Namespaced"
    },
    "ui": {
      "editor": {
        "name": "workopenclustermanagementio-manifestworkreplicaset-editor",
        "version": "sha256:7a8e2e9cb50b2f089bd2abce5b14fc837cd67a8930090152ea344f407db2c139",
        "sourceRef": {
          "apiGroup": "source.toolkit.fluxcd.io",
          "kind": "HelmRepository",
          "name": "appscode-charts-oci"
        }
      },
      "enforceQuota": false
    }
  }
}